bot/__init__.py
bot/cyborg.py
utils/__init__.py
utils/config.py
utils/file_util.py
retan-0.1.6.dist-info/entry_points.txt
retan-0.1.6.dist-info/METADATA
retan-0.1.6.dist-info/WHEEL
retan-0.1.6.dist-info/RECORD
