Metadata-Version: 2.3
Name: retan
Version: 0.1.6
Summary: A cli helper tool that helps with day to day cli commands and automates software development
License: MIT
Keywords: cli,python,automation,textual,configuration,development
Author: tanveer
Author-email: tanvoid0@gmail.com
Requires-Python: >=3.8,<3.13
Classifier: License :: OSI Approved :: MIT License
Classifier: Programming Language :: Python :: 3
Classifier: Programming Language :: Python :: 3.8
Classifier: Programming Language :: Python :: 3.9
Classifier: Programming Language :: Python :: 3.10
Classifier: Programming Language :: Python :: 3.11
Classifier: Programming Language :: Python :: 3.12
Requires-Dist: click
Requires-Dist: colorama
Requires-Dist: ollama
Requires-Dist: textual
